{
  "data": {
    "user": {
      "pinnedItems": {
        "totalCount": 6,
        "edges": [
          {
            "node": {
              "name": "jax",
              "description": "Composable transformations of Python+NumPy programs: differentiate, vectorize, JIT to GPU/TPU, and more",
              "url": "https://github.com/jax-ml/jax",
              "homepageUrl": "https://docs.jax.dev",
              "forkCount": 3213,
              "stargazers": {
                "totalCount": 33789
              },
              "watchers": {
                "totalCount": 324
              }
            }
          },
          {
            "node": {
              "name": "tinygp",
              "description": "The tiniest of Gaussian Process libraries",
              "url": "https://github.com/dfm/tinygp",
              "homepageUrl": "https://tinygp.readthedocs.io",
              "forkCount": 32,
              "stargazers": {
                "totalCount": 322
              },
              "watchers": {
                "totalCount": 6
              }
            }
          },
          {
            "node": {
              "name": "emcee",
              "description": "The Python ensemble sampling toolkit for affine-invariant MCMC",
              "url": "https://github.com/dfm/emcee",
              "homepageUrl": "https://emcee.readthedocs.io",
              "forkCount": 439,
              "stargazers": {
                "totalCount": 1540
              },
              "watchers": {
                "totalCount": 81
              }
            }
          },
          {
            "node": {
              "name": "corner.py",
              "description": "Make some beautiful corner plots",
              "url": "https://github.com/dfm/corner.py",
              "homepageUrl": "http://corner.readthedocs.io",
              "forkCount": 234,
              "stargazers": {
                "totalCount": 546
              },
              "watchers": {
                "totalCount": 15
              }
            }
          },
          {
            "node": {
              "name": "exoplanet",
              "description": "Fast & scalable MCMC for all your exoplanet needs! ",
              "url": "https://github.com/exoplanet-dev/exoplanet",
              "homepageUrl": "https://docs.exoplanet.codes",
              "forkCount": 54,
              "stargazers": {
                "totalCount": 225
              },
              "watchers": {
                "totalCount": 17
              }
            }
          },
          {
            "node": {
              "name": "daft",
              "description": "Render probabilistic graphical models using matplotlib",
              "url": "https://github.com/daft-dev/daft",
              "homepageUrl": "https://docs.daft-pgm.org",
              "forkCount": 119,
              "stargazers": {
                "totalCount": 682
              },
              "watchers": {
                "totalCount": 14
              }
            }
          }
        ]
      }
    }
  }
}